abism/__init__.py
abism/__main__.py
abism/answer.py
abism/run.py
abism/util.py
abism/back/ImageFunction.py
abism/back/Strehl.py
abism/back/__init__.py
abism/back/fit_helper.py
abism/back/fit_template_function.py
abism/back/image_info.py
abism/back/leastsqbound.py
abism/back/read_header.py
abism/back/strehl_fit.py
abism/doc/abism_v0.900.png
abism/doc/advanced_manual.pdf
abism/doc/idea.md
abism/doc/interface.md
abism/front/AnswerReturn.py
abism/front/__init__.py
abism/front/artist.py
abism/front/frame_plot.py
abism/front/frame_text.py
abism/front/matplotlib_extension.py
abism/front/menu_bar.py
abism/front/pick.py
abism/front/tk_extension.py
abism/front/util_front.py
abism/front/window_root.py
abism/plugin/__init__.py
abism/plugin/gtk_window_open.py
abism/plugin/histogram.py
abism/plugin/profile_line.py
abism/plugin/stat_rectangle.py
abism/plugin/window_debug.py
abism/plugin/window_text.py
abism/plugin/window_xterm.py
abism/res/arrow_down.gif
abism/res/arrow_up.gif
abism/res/bato_chico.gif
abism-0.911.data/scripts/abism
abism-0.911.dist-info/METADATA
abism-0.911.dist-info/WHEEL
abism-0.911.dist-info/top_level.txt
abism-0.911.dist-info/RECORD
