Metadata-Version: 2.1
Name: abism
Version: 0.911
Summary: Adaptative Background Interferometric Strehl Meter,Graphical user interface (GUI) to mesure Astrophysics image quality (Strehl ratio)
Home-page: https://github.com/tinmarino/abism
Author: Julien Girard, Martin Tourneboeuf
Author-email: tinmarino@gmail.com
License: UNKNOWN
Platform: UNKNOWN
Classifier: Programming Language :: Python :: 3
Classifier: License :: OSI Approved :: MIT License
Classifier: Operating System :: OS Independent
Requires-Dist: matplotlib
Requires-Dist: scipy
Requires-Dist: numpy
Requires-Dist: astropy
